Workbook

Sheet Sheet1
A1: isco4_code | B1: occupation | C1: mean_exposure | D1: sd_exposure | E1: n_tasks | F1: status | G1: gradient | H1: 2010 SOC Code | I1: 2010 SOC Title
A2: 4132 | B2: 4132 - Data entry clerks | C2: 0.7 | D2: 0.0286 | E2: 5 | F2: Exposed | G2: Gradient 4 | H2: =VLOOKUP(A2,'ISCO-08 to 2010 SOC'!$A$8:$E$1132,4,FALSE) -> 43-9021 | I2: =VLOOKUP(A2,'ISCO-08 to 2010 SOC'!$A$8:$E$1132,5,FALSE) -> Data Entry Keyers
A3: 4131 | B3: 4131 - Typists and word processing operators | C3: 0.6521 | D3: 0.0528 | E3: 7 | F3: Exposed | G3: Gradient 4 | H3: =VLOOKUP(A3,'ISCO-08 to 2010 SOC'!$A$8:$E$1132,4,FALSE) -> 43-9022 | I3: =VLOOKUP(A3,'ISCO-08 to 2010 SOC'!$A$8:$E$1132,5,FALSE) -> Word Processors and Typists
A4: 4311 | B4: 4311 - Accounting and bookkeeping clerks | C4: 0.64 | D4: 0.0725 | E4: 5 | F4: Exposed | G4: Gradient 4 | H4: =VLOOKUP(A4,'ISCO-08 to 2010 SOC'!$A$8:$E$1132,4,FALSE) -> 43-3021 | I4: =VLOOKUP(A4,'ISCO-08 to 2010 SOC'!$A$8:$E$1132,5,FALSE) -> Billing and Posting Clerks
A5: 4312 | B5: 4312 - Statistical, finance and insurance clerks | C5: 0.6395 | D5: 0.0243 | E5: 5 | F5: Exposed | G5: Gradient 4 | H5: =VLOOKUP(A5,'ISCO-08 to 2010 SOC'!$A$8:$E$1132,4,FALSE) -> 43-3099 | I5: =VLOOKUP(A5,'ISCO-08 to 2010 SOC'!$A$8:$E$1132,5,FALSE) -> Financial Clerks, All Other
A6: 3311 | B6: 3311 - Securities and finance dealers and brokers | C6: 0.6314 | D6: 0.0377 | E6: 5 | F6: Exposed | G6: Gradient 4 | H6: =VLOOKUP(A6,'ISCO-08 to 2010 SOC'!$A$8:$E$1132,4,FALSE) -> 41-1012 | I6: =VLOOKUP(A6,'ISCO-08 to 2010 SOC'!$A$8:$E$1132,5,FALSE) -> First-Line Supervisors of Non-Retail Sales Workers
A7: 4419 | B7: 4419 - Clerical support workers not elsewhere classified | C7: 0.6279 | D7: 0.0261 | E7: 4 | F7: Exposed | G7: Gradient 4 | H7: =VLOOKUP(A7,'ISCO-08 to 2010 SOC'!$A$8:$E$1132,4,FALSE) -> 43-4021 | I7: =VLOOKUP(A7,'ISCO-08 to 2010 SOC'!$A$8:$E$1132,5,FALSE) -> Correspondence Clerks
A8: 2413 | B8: 2413 - Financial analysts | C8: 0.6181 | D8: 0.0614 | E8: 9 | F8: Exposed | G8: Gradient 4 | H8: =VLOOKUP(A8,'ISCO-08 to 2010 SOC'!$A$8:$E$1132,4,FALSE) -> 13-2041 | I8: =VLOOKUP(A8,'ISCO-08 to 2010 SOC'!$A$8:$E$1132,5,FALSE) -> Credit Analysts
A9: 5244 | B9: 5244 - Contact centre salespersons | C9: 0.6116 | D9: 0.1015 | E9: 8 | F9: Exposed | G9: Gradient 4 | H9: =VLOOKUP(A9,'ISCO-08 to 2010 SOC'!$A$8:$E$1132,4,FALSE) -> 41-9041 | I9: =VLOOKUP(A9,'ISCO-08 to 2010 SOC'!$A$8:$E$1132,5,FALSE) -> Telemarketers
A10: 4313 | B10: 4313 - Payroll clerks | C10: 0.6065 | D10: 0.0765 | E10: 5 | F10: Exposed | G10: Gradient 4 | H10: =VLOOKUP(A10,'ISCO-08 to 2010 SOC'!$A$8:$E$1132,4,FALSE) -> 43-3051 | I10: =VLOOKUP(A10,'ISCO-08 to 2010 SOC'!$A$8:$E$1132,5,FALSE) -> Payroll and Timekeeping Clerks
A11: 3312 | B11: 3312 - Credit and loans officers | C11: 0.605 | D11: 0.0392 | E11: 6 | F11: Exposed | G11: Gradient 4 | H11: =VLOOKUP(A11,'ISCO-08 to 2010 SOC'!$A$8:$E$1132,4,FALSE) -> 13-2071 | I11: =VLOOKUP(A11,'ISCO-08 to 2010 SOC'!$A$8:$E$1132,5,FALSE) -> Credit Counselors
A12: 4416 | B12: 4416 - Personnel clerks | C12: 0.605 | D12: 0.0892 | E12: 7 | F12: Exposed | G12: Gradient 4 | H12: =VLOOKUP(A12,'ISCO-08 to 2010 SOC'!$A$8:$E$1132,4,FALSE) -> 43-4161 | I12: =VLOOKUP(A12,'ISCO-08 to 2010 SOC'!$A$8:$E$1132,5,FALSE) -> Human Resources Assistants, Except Payroll and Timekeeping
A13: 2513 | B13: 2513 - Web and multimedia developers | C13: 0.6045 | D13: 0.0809 | E13: 5 | F13: Exposed | G13: Gradient 4 | H13: =VLOOKUP(A13,'ISCO-08 to 2010 SOC'!$A$8:$E$1132,4,FALSE) -> 15-1134 | I13: =VLOOKUP(A13,'ISCO-08 to 2010 SOC'!$A$8:$E$1132,5,FALSE) -> Web Developers
... A428: 7112 | B428: 7112 - Bricklayers and related workers | C428: 0.0887 | D428: 0.012 | E428: 3 | F428: Not Exposed | G428: Not Exposed | H428: =VLOOKUP(A428,'ISCO-08 to 2010 SOC'!$A$8:$E$1132,4,FALSE) -> 47-2021 | I428: =VLOOKUP(A428,'ISCO-08 to 2010 SOC'!$A$8:$E$1132,5,FALSE) -> Brickmasons and Blockmasons

Sheet ISCO-08 to 2010 SOC
A1: Bureau of Labor Statistics
A2: On behalf of the Standard Occupational Classification Policy Committee (SOCPC)
A4: August 2012 (Updated June 2015)
A5: Questions should be emailed to soc@bls.gov
A7: ISCO-08 Code | B7: ISCO-08 Title EN | C7: part | D7: 2010 SOC Code | E7: 2010 SOC Title | F7: Comment 8/17/11
A8: 0110 | B8: Commissioned armed forces officers | C8: * | D8: 55-1011 | E8: Air Crew Officers
A9: 0110 | B9: Commissioned armed forces officers | C9: * | D9: 55-1012 | E9: Aircraft Launch and Recovery Officers
A10: 0110 | B10: Commissioned armed forces officers | C10: * | D10: 55-1013 | E10: Armored Assault Vehicle Officers
A11: 0110 | B11: Commissioned armed forces officers | C11: * | D11: 55-1014 | E11: Artillery and Missile Officers
A12: 0110 | B12: Commissioned armed forces officers | C12: * | D12: 55-1015 | E12: Command and Control Center Officers
A13: 0110 | B13: Commissioned armed forces officers | C13: * | D13: 55-1016 | E13: Infantry Officers
A14: 0110 | B14: Commissioned armed forces officers | C14: * | D14: 55-1017 | E14: Special Forces Officers
A15: 0110 | B15: Commissioned armed forces officers | C15: * | D15: 55-1019 | E15: Military Officer Special and Tactical Operations Leaders, All Other
A16: 0210 | B16: Non-commissioned armed forces officers | C16: * | D16: 55-2011 | E16: First-Line Supervisors of Air Crew Members
A17: 0210 | B17: Non-commissioned armed forces officers | C17: * | D17: 55-2012 | E17: First-Line Supervisors of Weapons Specialists/Crew Members
A18: 0210 | B18: Non-commissioned armed forces officers | C18: * | D18: 55-2013 | E18: First-Line Supervisors of All Other Tactical Operations Specialists
A19: 0310 | B19: Armed forces occupations, other ranks | C19: * | D19: 55-3011 | E19: Air Crew Members
... A27: 0310 | B27: Armed forces occupations, other ranks | C27: * | D27: 55-3019 | E27: Military Enlisted Tactical Operations and Air/Weapons Specialists and Crew Members, All Other
A28: 1111 | B28: Legislators | D28: 11-1031 | E28: Legislators
A29: 1112 | B29: Senior government officials | C29: * | D29: 11-1011 | E29: Chief Executives
A30: 1112 | B30: Senior government officials | C30: * | D30: 11-1021 | E30: General and Operations Managers
A31: 1112 | B31: Senior government officials | C31: * | D31: 11-9161 | E31: Emergency Management Directors
A32: 1113 | B32: Traditional chiefs and heads of villages | C32: * | D32: 11-1011 | E32: Chief Executives
A33: 1113 | B33: Traditional chiefs and heads of villages | C33: * | D33: 11-1031 | E33: Legislators
A34: 1114 | B34: Senior officials of special-interest organizations | C34: * | D34: 11-1021 | E34: General and Operations Managers
A35: 1114 | B35: Senior officials of special-interest organizations | C35: * | D35: 11-2031 | E35: Public Relations and Fundraising Managers
A36: 1114 | B36: Senior officials of special-interest organizations | C36: * | D36: 11-9199 | E36: Managers, All Other
A37: 1120 | B37: Managing directors and chief executives | C37: * | D37: 11-1011 | E37: Chief Executives
A38: 1120 | B38: Managing directors and chief executives | C38: * | D38: 11-1021 | E38: General and Operations Managers
A39: 1211 | B39: Finance managers | D39: 11-3031 | E39: Financial Managers
A40: 1212 | B40: Human resource managers | C40: * | D40: 11-3111 | E40: Compensation and Benefits Managers
A41: 1212 | B41: Human resource managers | C41: * | D41: 11-3121 | E41: Human Resources Managers
A42: 1212 | B42: Human resource managers | C42: * | D42: 11-3131 | E42: Training and Development Managers
A43: 1213 | B43: Policy and planning managers | D43: 11-9199 | E43: Managers, All Other
A44: 1219 | B44: Business services and administration managers not elsewhere classified | C44: * | D44: 11-2031 | E44: Public Relations and Fundraising Managers
A45: 1219 | B45: Business services and administration managers not elsewhere classified | C45: * | D45: 11-3011 | E45: Administrative Services Managers
A46: 1219 | B46: Business services and administration managers not elsewhere classified | C46: * | D46: 11-3061 | E46: Purchasing Managers
A47: 1219 | B47: Business services and administration managers not elsewhere classified | C47: * | D47: 11-9061 | E47: Funeral Service Managers
A48: 1219 | B48: Business services and administration managers not elsewhere classified | C48: * | D48: 11-9131 | E48: Postmasters and Mail Superintendents
A49: 1219 | B49: Business services and administration managers not elsewhere classified | C49: * | D49: 11-9199 | E49: Managers, All Other
A50: 1221 | B50: Sales and marketing managers | C50: * | D50: 11-2021 | E50: Marketing Managers
A51: 1221 | B51: Sales and marketing managers | C51: * | D51: 11-2022 | E51: Sales Managers
A52: 1222 | B52: Advertising and public relations managers | C52: * | D52: 11-2011 | E52: Advertising and Promotions Managers
A53: 1222 | B53: Advertising and public relations managers | C53: * | D53: 11-2031 | E53: Public Relations and Fundraising Managers
A54: 1223 | B54: Research and development managers | C54: * | D54: 11-9041 | E54: Architectural and Engineering Managers
A55: 1223 | B55: Research and development managers | C55: * | D55: 11-9121 | E55: Natural Sciences Managers
A56: 1311 | B56: Agricultural and forestry production managers | D56: 11-9013 | E56: Farmers, Ranchers, and Other Agricultural Managers
A57: 1312 | B57: Aquaculture and fisheries production managers | D57: 11-9013 | E57: Farmers, Ranchers, and Other Agricultural Managers
A58: 1321 | B58: Manufacturing managers | D58: 11-3051 | E58: Industrial Production Managers
A59: 1322 | B59: Mining managers | D59: 11-9199 | E59: Managers, All Other
A60: 1323 | B60: Construction managers | D60: 11-9021 | E60: Construction Managers
A61: 1324 | B61: Supply, distribution and related managers | D61: 11-3071 | E61: Transportation, Storage, and Distribution Managers
A62: 1330 | B62: Information and communications technology service managers | D62: 11-3021 | E62: Computer and Information Systems Managers
A63: 1341 | B63: Child care services managers | D63: 11-9031 | E63: Education Administrators, Preschool and Childcare Center/Program
A64: 1342 | B64: Health services managers | D64: 11-9111 | E64: Medical and Health Services Managers
A65: 1343 | B65: Aged care services managers | C65: * | D65: 11-1021 | E65: General and Operations Managers
A66: 1343 | B66: Aged care services managers | C66: * | D66: 11-9111 | E66: Medical and Health Services Managers
A67: 1344 | B67: Social welfare managers | D67: 11-9151 | E67: Social and Community Service Managers
A68: 1345 | B68: Education managers | C68: * | D68: 11-9032 | E68: Education Administrators, Elementary and Secondary School
A69: 1345 | B69: Education managers | C69: * | D69: 11-9033 | E69: Education Administrators, Postsecondary
A70: 1345 | B70: Education managers | C70: * | D70: 11-9039 | E70: Education Administrators, All Other
A71: 1346 | B71: Financial and insurance services branch managers | C71: * | D71: 11-1021 | E71: General and Operations Managers
A72: 1346 | B72: Financial and insurance services branch managers | C72: * | D72: 11-3031 | E72: Financial Managers
A73: 1349 | B73: Professional services managers not elsewhere classified | D73: 11-9199 | E73: Managers, All Other
A74: 1411 | B74: Hotel managers | D74: 11-9081 | E74: Lodging Managers
A75: 1412 | B75: Restaurant managers | D75: 11-9051 | E75: Food Service Managers
A76: 1420 | B76: Retail and wholesale trade managers | D76: 11-1021 | E76: General and Operations Managers
A77: 1431 | B77: Sports, recreation and cultural centre managers | C77: * | D77: 11-9071 | E77: Gaming Managers
A78: 1431 | B78: Sports, recreation and cultural centre managers | C78: * | D78: 11-9199 | E78: Managers, All Other
A79: 1439 | B79: Services managers not elsewhere classified | D79: 11-9199 | E79: Managers, All Other
A80: 211 | B80: Physical and earth science professionals | D80: 19-2099 | E80: Physical Scientists, All Other | F80: matches to 3-digit ISCO
A81: 2111 | B81: Physicists and astronomers | C81: * | D81: 19-2011 | E81: Astronomers
A82: 2111 | B82: Physicists and astronomers | C82: * | D82: 19-2012 | E82: Physicists
A83: 2112 | B83: Meteorologists | D83: 19-2021 | E83: Atmospheric and Space Scientists
A84: 2113 | B84: Chemists | C84: * | D84: 19-2031 | E84: Chemists
A85: 2113 | B85: Chemists | C85: * | D85: 19-2032 | E85: Materials Scientists
A86: 2114 | B86: Geologists and geophysicists | C86: * | D86: 19-2042 | E86: Geoscientists, Except Hydrologists and Geographers
A87: 2114 | B87: Geologists and geophysicists | C87: * | D87: 19-2043 | E87: Hydrologist
A88: 2120 | B88: Mathematicians, actuaries and statisticians | C88: * | D88: 15-2011 | E88: Actuaries
A89: 2120 | B89: Mathematicians, actuaries and statisticians | C89: * | D89: 15-2021 | E89: Mathematicians
A90: 2120 | B90: Mathematicians, actuaries and statisticians | C90: * | D90: 15-2031 | E90: Operations Research Analysts
A91: 2120 | B91: Mathematicians, actuaries and statisticians | C91: * | D91: 15-2041 | E91: Statisticians
A92: 2120 | B92: Mathematicians, actuaries and statisticians | C92: * | D92: 19-3022 | E92: Survey Researchers
A93: 2131 | B93: Biologists, botanists, zoologists and related professionals | C93: * | D93: 19-1011 | E93: Animal Scientists
A94: 2131 | B94: Biologists, botanists, zoologists and related professionals | C94: * | D94: 19-1012 | E94: Food Scientists and Technologists | F94: recommended match 8/18/11
A95: 2131 | B95: Biologists, botanists, zoologists and related professionals | C95: * | D95: 19-1013 | E95: Soil and Plant Scientists
A96: 2131 | B96: Biologists, botanists, zoologists and related professionals | C96: * | D96: 19-1021 | E96: Biochemists and Biophysicists
A97: 2131 | B97: Biologists, botanists, zoologists and related professionals | C97: * | D97: 19-1022 | E97: Microbiologists
A98: 2131 | B98: Biologists, botanists, zoologists and related professionals | C98: * | D98: 19-1023 | E98: Zoologists and Wildlife Biologists
A99: 2131 | B99: Biologists, botanists, zoologists and related professionals | C99: * | D99: 19-1029 | E99: Biological Scientists, All Other
A100: 2131 | B100: Biologists, botanists, zoologists and related professionals | C100: * | D100: 19-1041 | E100: Epidemiologists
A101: 2131 | B101: Biologists, botanists, zoologists and related professionals | C101: * | D101: 19-1042 | E101: Medical Scientists, Except Epidemiologists
A102: 2131 | B102: Biologists, botanists, zoologists and related professionals | C102: * | D102: 19-1099 | E102: Life Scientists, All Other
A103: 2132 | B103: Farming, forestry and fisheries advisers | C103: * | D103: 19-1013 | E103: Soil and Plant Scientists
A104: 2132 | B104: Farming, forestry and fisheries advisers | C104: * | D104: 19-1032 | E104: Foresters
A105: 2132 | B105: Farming, forestry and fisheries advisers | C105: * | D105: 25-9021 | E105: Farm and Home Management Advisors
A106: 2133 | B106: Environmental protection professionals | C106: * | D106: 19-1031 | E106: Conservation Scientists
A107: 2133 | B107: Environmental protection professionals | C107: * | D107: 19-2041 | E107: Environmental Scientists and Specialists, Including Health
A108: 2141 | B108: Industrial and production engineers | D108: 17-2112 | E108: Industrial Engineers
A109: 2142 | B109: Civil engineers | D109: 17-2051 | E109: Civil Engineers
...

Sheet Sayfa2
